MANIFEST.in
README.rst
VERSION.txt
requirements-test.txt
requirements.txt
setup.py
util.py
async/__init__.py
async/call.py
async/queue.py
async/state.py
gevent_async.egg-info/PKG-INFO
gevent_async.egg-info/SOURCES.txt
gevent_async.egg-info/dependency_links.txt
gevent_async.egg-info/not-zip-safe
gevent_async.egg-info/requires.txt
gevent_async.egg-info/top_level.txt